base_astro_bot/__init__.py
base_astro_bot/base_bot.py
base_astro_bot/base_mixin.py
base_astro_bot/database/__init__.py
base_astro_bot/database/database_manager.py
base_astro_bot/database/database_models.py
base_astro_bot/fleet/__init__.py
base_astro_bot/fleet/fleet_mixin.py
base_astro_bot/rsi_data/__init__.py
base_astro_bot/rsi_data/loaners.py
base_astro_bot/rsi_data/road_map.py
base_astro_bot/rsi_data/road_map_mixin.py
base_astro_bot/rsi_data/rsi_mixin.py
base_astro_bot/rsi_data/rsi_parser.py
base_astro_bot/trade/__init__.py
base_astro_bot/trade/data_rat_client.py
base_astro_bot/trade/trade_assistant.py
base_astro_bot/trade/trade_mixin.py
base_astro_bot/trade/data_structure/__init__.py
base_astro_bot/trade/data_structure/data_classes.py
base_astro_bot/trade/data_structure/data_structure.py
base_astro_bot/trade/data_structure/trade_classes.py
base_astro_bot/utils/__init__.py
base_astro_bot/utils/install.py
base_astro_bot/utils/my_logger.py
tests/artifacts/__init__.py
tests/artifacts/mock_trade.py
tests/artifacts/sample_ships_data.py
base_astro_bot-1.3.6.dist-info/LICENSE
base_astro_bot-1.3.6.dist-info/METADATA
base_astro_bot-1.3.6.dist-info/WHEEL
base_astro_bot-1.3.6.dist-info/top_level.txt
base_astro_bot-1.3.6.dist-info/RECORD
