Metadata-Version: 2.1
Name: base-astro-bot
Version: 1.3.6
Summary: Base bot class for Star Citizen players
Home-page: https://github.com/Mirdalan/base_astro_bot
Author: Michal Chrzanowski
Author-email: michrzan@gmail.com
License: MIT
Keywords: star citizen discord spectrum bot
Platform: UNKNOWN
Classifier: Development Status :: 4 - Beta
Classifier: Intended Audience :: Developers
Classifier: Topic :: Games/Entertainment
Classifier: License :: OSI Approved :: MIT License
Classifier: Programming Language :: Python :: 3.5
Classifier: Programming Language :: Python :: 3.6
Requires-Python: ~=3.5
Requires-Dist: pafy (==0.5.4)
Requires-Dist: pymongo (==3.7.2)
Requires-Dist: requests (==2.20.1)
Requires-Dist: SQLAlchemy (==1.2.14)
Requires-Dist: tabulate (==0.8.2)
Requires-Dist: youtube-dl (==2018.11.23)
Requires-Dist: websocket-client (==0.44.0) ; "linux" in sys_platform
Requires-Dist: websocket-client (==0.46.0) ; sys_platform == "win32"
